anachem/AnaChem.py
anachem/AnalyseChemistry.py
anachem/__init__.py
anachem/roundac.py
anachem/roundbase.py
anachem-0.20.dist-info/METADATA
anachem-0.20.dist-info/WHEEL
anachem-0.20.dist-info/top_level.txt
anachem-0.20.dist-info/RECORD
