Metadata-Version: 2.1
Name: anachem
Version: 0.20
Summary: errors and statistical treatment of analytical data
Author: 杨涛
